{"nodes": [{"id": "c_clg_cobbleai_backend_gen_keys_py", "label": "gen_keys.py", "file_type": "code", "source_file": "C:\\CLG\\cobbleAI\\backend\\gen_keys.py", "source_location": "L1"}], "edges": [{"source": "c_clg_cobbleai_backend_gen_keys_py", "target": "cryptography_hazmat_primitives", "relation": "imports_from", "confidence": "EXTRACTED", "source_file": "C:\\CLG\\cobbleAI\\backend\\gen_keys.py", "source_location": "L1", "weight": 1.0}, {"source": "c_clg_cobbleai_backend_gen_keys_py", "target": "cryptography_hazmat_primitives_asymmetric", "relation": "imports_from", "confidence": "EXTRACTED", "source_file": "C:\\CLG\\cobbleAI\\backend\\gen_keys.py", "source_location": "L2", "weight": 1.0}, {"source": "c_clg_cobbleai_backend_gen_keys_py", "target": "os", "relation": "imports", "confidence": "EXTRACTED", "source_file": "C:\\CLG\\cobbleAI\\backend\\gen_keys.py", "source_location": "L3", "weight": 1.0}], "raw_calls": []}